tribble/main.py
tribble-0.0.1.dist-info/METADATA
tribble-0.0.1.dist-info/WHEEL
tribble-0.0.1.dist-info/top_level.txt
tribble-0.0.1.dist-info/RECORD
