Metadata-Version: 2.1
Name: tribble
Version: 0.0.1
Summary: A example Python package
Home-page: https://github.com/hansolosan/tribble
Author: Radu Florian
Author-email: raduf@us.ibm.com
License: Apache
Classifier: Development Status :: 1 - Planning
Classifier: Intended Audience :: Science/Research
Classifier: License :: OSI Approved :: BSD License
Classifier: Operating System :: POSIX :: Linux
Classifier: Programming Language :: Python :: 2
Classifier: Programming Language :: Python :: 2.7
Classifier: Programming Language :: Python :: 3
Classifier: Programming Language :: Python :: 3.4
Classifier: Programming Language :: Python :: 3.5
